bnemo/__init__.py
bnemo/bnemo.py
bnemo/emo_unicode.py
bnemo-1.0.1.dist-info/LICENSE
bnemo-1.0.1.dist-info/METADATA
bnemo-1.0.1.dist-info/WHEEL
bnemo-1.0.1.dist-info/top_level.txt
bnemo-1.0.1.dist-info/RECORD
