Metadata-Version: 2.1
Name: bnemo
Version: 1.0.1
Summary: A Python package for translating Emoji and Emoticons into Bengali text.
Home-page: https://github.com/faruk-ahmad/bnemo
Author: Faruk Ahmad, Sagor Sarkar
Author-email: faruk.csebrur@gmail.com, sagorhem3532@gmail.com
License: MIT
Platform: UNKNOWN
Classifier: Programming Language :: Python :: 3
Classifier: License :: OSI Approved :: MIT License
Classifier: Operating System :: OS Independent
Requires-Python: >=3.5
